[
  {
    "id": "C205649164",
    "label": "Geography",
    "count": 13
  },
  {
    "id": "C39432304",
    "label": "Environmental science",
    "count": 12
  },
  {
    "id": "C62649853",
    "label": "Remote sensing",
    "count": 8
  },
  {
    "id": "C18903297",
    "label": "Ecology",
    "count": 7
  },
  {
    "id": "C86803240",
    "label": "Biology",
    "count": 7
  },
  {
    "id": "C41008148",
    "label": "Computer science",
    "count": 7
  },
  {
    "id": "C153294291",
    "label": "Meteorology",
    "count": 7
  },
  {
    "id": "C2779343474",
    "label": "Context (archaeology)",
    "count": 6
  },
  {
    "id": "C97137747",
    "label": "Forestry",
    "count": 6
  },
  {
    "id": "C2777601987",
    "label": "Disturbance (geology)",
    "count": 5
  }
]